[
  {
    "title": "South Beach",
    "img": "https://images.unsplash.com/photo-1499394515978-b4a3c206c0ed?auto=format&fit=crop&w=800&q=80"
  },
  {
    "title": "Everglades National Park",
    "img": "https://images.unsplash.com/photo-1615384244079-4d82c5d28f8b?auto=format&fit=crop&w=800&q=80"
  },
  {
    "title": "Art Deco Historic District",
    "img": "https://images.unsplash.com/photo-1522093125933-4f358dce4a18?auto=format&fit=crop&w=800&q=80"
  },
  {
    "title": "Little Havana",
    "img": "https://images.unsplash.com/photo-1607606451552-1b9902c630f0?auto=format&fit=crop&w=800&q=80"
  },
  {
    "title": "Wynwood Walls",
    "img": "https://images.unsplash.com/photo-1530440480852-44b7f99f34ee?auto=format&fit=crop&w=800&q=80"
  },
  {
    "title": "Vizcaya Museum & Gardens",
    "img": "https://images.unsplash.com/photo-1571162995730-b26e1d579ceb?auto=format&fit=crop&w=800&q=80"
  },
  {
    "title": "Bayside Marketplace",
    "img": "https://images.unsplash.com/photo-1561101238-73e18ce617c3?auto=format&fit=crop&w=800&q=80"
  },
  {
    "title": "Coconut Grove",
    "img": "https://images.unsplash.com/photo-1558875924-5ee67e3307a8?auto=format&fit=crop&w=800&q=80"
  },
  {
    "title": "Key Biscayne Bike Trail",
    "img": "https://images.unsplash.com/photo-1533616688413-6a70a37f29b5?auto=format&fit=crop&w=800&q=80"
  },
  {
    "title": "Venetian Pool (Coral Gables)",
    "img": "https://images.unsplash.com/photo-1599058917212-18c52a32f50a?auto=format&fit=crop&w=800&q=80"
  }
]
